[
 {
   "Surname": "Merritt",
   "Name": "LaShawn",
   "Nationality": "USA",
   "Round": "Fi",
   "RT": "0,161",
   "t400m": "44,06",
   "t200m": "21,49",
   "Diff.": "1,08",
   "t200-400m": "22,57",
   "t300m": "32,32",
   "t100m": "11,14",
   "t100-200": "10,35",
   "t200-300m": "10,83",
   "t300-400m": "11,74"
 },
 {
   "Surname": "",
   "Name": "",
   "Nationality": "",
   "Round": "Ht 2",
   "RT": "0,163",
   "t400m": "44,37",
   "t200m": "21,51",
   "Diff.": "1,35",
   "t200-400m": "22,86",
   "t300m": "32,50",
   "t100m": "10,94",
   "t100-200": "10,57",
   "t200-300m": "10,99",
   "t300-400m": "11,87"
 },
 {
   "Surname": "Wariner",
   "Name": "Jeremy",
   "Nationality": "USA",
   "Round": "Fi",
   "RT": "0,162",
   "t400m": "44,60",
   "t200m": "21,41",
   "Diff.": "1,78",
   "t200-400m": "23,19",
   "t300m": "32,34",
   "t100m": "10,98",
   "t100-200": "10,43",
   "t200-300m": "10,93",
   "t300-400m": "12,26"
 },
 {
   "Surname": "",
   "Name": "",
   "Nationality": "",
   "Round": "Ht 1",
   "RT": "0,189",
   "t400m": "44,69",
   "t200m": "21,63",
   "Diff.": "1,43",
   "t200-400m": "23,06",
   "t300m": "32,48",
   "t100m": "11,11",
   "t100-200": "10,52",
   "t200-300m": "10,85",
   "t300-400m": "12,21"
 },
 {
   "Surname": "Quow",
   "Name": "Renny",
   "Nationality": "TRI",
   "Round": "Fi",
   "RT": "0,195",
   "t400m": "45,02",
   "t200m": "22,43",
   "Diff.": "0,16",
   "t200-400m": "22,59",
   "t300m": "33,32",
   "t100m": "11,70",
   "t100-200": "10,73",
   "t200-300m": "10,89",
   "t300-400m": "11,70"
 },
 {
   "Surname": "",
   "Name": "",
   "Nationality": "",
   "Round": "Ht 2",
   "RT": "0,248",
   "t400m": "44,53",
   "t200m": "",
   "Diff.": "",
   "t200-400m": "",
   "t300m": "32,97",
   "t100m": "",
   "t100-200": "",
   "t200-300m": "",
   "t300-400m": "11,56"
 },
 {
   "Surname": "Henry",
   "Name": "Tabarie",
   "Nationality": "ISV",
   "Round": "Fi",
   "RT": "0,162",
   "t400m": "45,42",
   "t200m": "21,83",
   "Diff.": "1,76",
   "t200-400m": "23,59",
   "t300m": "33,17",
   "t100m": "11,18",
   "t100-200": "10,65",
   "t200-300m": "11,34",
   "t300-400m": "12,25"
 },
 {
   "Surname": "",
   "Name": "",
   "Nationality": "",
   "Round": "Ht 3",
   "RT": "0,146",
   "t400m": "44,97",
   "t200m": "21,91",
   "Diff.": "1,15",
   "t200-400m": "23,06",
   "t300m": "32,89",
   "t100m": "11,22",
   "t100-200": "10,69",
   "t200-300m": "10,98",
   "t300-400m": "12,08"
 },
 {
   "Surname": "Brown",
   "Name": "Chris",
   "Nationality": "BAH",
   "Round": "Fi",
   "RT": "0,161",
   "t400m": "45,47",
   "t200m": "21,31",
   "Diff.": "2,85",
   "t200-400m": "24,16",
   "t300m": "32,53",
   "t100m": "10,98",
   "t100-200": "10,33",
   "t200-300m": "11,22",
   "t300-400m": "12,94"
 },
 {
   "Surname": "",
   "Name": "",
   "Nationality": "",
   "Round": "Ht 3",
   "RT": "0,129",
   "t400m": "44,95",
   "t200m": "21,72",
   "Diff.": "1,51",
   "t200-400m": "23,23",
   "t300m": "32,84",
   "t100m": "11,08",
   "t100-200": "10,64",
   "t200-300m": "11,12",
   "t300-400m": "12,11"
 },
 {
   "Surname": "Gillick",
   "Name": "David",
   "Nationality": "IRL",
   "Round": "Fi",
   "RT": "0,148",
   "t400m": "45,53",
   "t200m": "21,83",
   "Diff.": "1,87",
   "t200-400m": "23,70",
   "t300m": "33,18",
   "t100m": "11,24",
   "t100-200": "10,59",
   "t200-300m": "11,35",
   "t300-400m": "12,35"
 },
 {
   "Surname": "",
   "Name": "",
   "Nationality": "",
   "Round": "Ht 1",
   "RT": "0,147",
   "t400m": "44,88",
   "t200m": "21,80",
   "Diff.": "1,28",
   "t200-400m": "23,08",
   "t300m": "32,77",
   "t100m": "11,27",
   "t100-200": "10,53",
   "t200-300m": "10,97",
   "t300-400m": "12,11"
 },
 {
   "Surname": "Bingham",
   "Name": "Michael",
   "Nationality": "GBR",
   "Round": "Fi",
   "RT": "0,172",
   "t400m": "45,56",
   "t200m": "21,84",
   "Diff.": "1,88",
   "t200-400m": "23,72",
   "t300m": "33,02",
   "t100m": "11,19",
   "t100-200": "10,65",
   "t200-300m": "11,18",
   "t300-400m": "12,54"
 },
 {
   "Surname": "",
   "Name": "",
   "Nationality": "",
   "Round": "Ht 1",
   "RT": "0,173",
   "t400m": "44,74",
   "t200m": "21,84",
   "Diff.": "1,06",
   "t200-400m": "22,90",
   "t300m": "32,76",
   "t100m": "11,15",
   "t100-200": "10,69",
   "t200-300m": "10,92",
   "t300-400m": "11,98"
 },
 {
   "Surname": "Djhone",
   "Name": "Leslie",
   "Nationality": "FRA",
   "Round": "Fi",
   "RT": "0,151",
   "t400m": "45,90",
   "t200m": "22,04",
   "Diff.": "1,82",
   "t200-400m": "23,86",
   "t300m": "33,46",
   "t100m": "11,34",
   "t100-200": "10,70",
   "t200-300m": "11,42",
   "t300-400m": "12,44"
 },
 {
   "Surname": "",
   "Name": "",
   "Nationality": "",
   "Round": "Ht 1",
   "RT": "0,165",
   "t400m": "44,80",
   "t200m": "21,87",
   "Diff.": "1,06",
   "t200-400m": "22,93",
   "t300m": "32,85",
   "t100m": "11,32",
   "t100-200": "10,55",
   "t200-300m": "10,98",
   "t300-400m": "11,95"
 },
 {
   "Surname": "Collazo",
   "Name": "William",
   "Nationality": "CUB",
   "Round": "Ht 2",
   "RT": "0,147",
   "t400m": "44,93",
   "t200m": "21,56",
   "Diff.": "1,81",
   "t200-400m": "23,37",
   "t300m": "32,67",
   "t100m": "10,97",
   "t100-200": "10,59",
   "t200-300m": "11,11",
   "t300-400m": "12,26"
 },
 {
   "Surname": "Miller",
   "Name": "Ramon",
   "Nationality": "BAH",
   "Round": "Ht 1",
   "RT": "0,157",
   "t400m": "44,99",
   "t200m": "21,99",
   "Diff.": "1,01",
   "t200-400m": "23,00",
   "t300m": "32,80",
   "t100m": "11,26",
   "t100-200": "10,73",
   "t200-300m": "10,81",
   "t300-400m": "12,19"
 },
 {
   "Surname": "Chambers Ricardo",
   "Name": "",
   "Nationality": "JAM",
   "Round": "Ht 3",
   "RT": "0,167",
   "t400m": "45,13",
   "t200m": "22,00",
   "Diff.": "1,13",
   "t200-400m": "23,13",
   "t300m": "32,88",
   "t100m": "11,28",
   "t100-200": "10,72",
   "t200-300m": "10,88",
   "t300-400m": "12,25"
 },
 {
   "Surname": "Borlée",
   "Name": "Kévin",
   "Nationality": "BEL",
   "Round": "Ht 3",
   "RT": "0,143",
   "t400m": "45,28",
   "t200m": "22,28",
   "Diff.": "0,72",
   "t200-400m": "23,00",
   "t300m": "33,34",
   "t100m": "11,40",
   "t100-200": "10,88",
   "t200-300m": "11,06",
   "t300-400m": "11,94"
 },
 {
   "Surname": "Wroe Sean",
   "Name": "",
   "Nationality": "AUS",
   "Round": "Ht 2",
   "RT": "0,160",
   "t400m": "45,32",
   "t200m": "21,52",
   "Diff.": "2,28",
   "t200-400m": "23,80",
   "t300m": "32,81",
   "t100m": "11,03",
   "t100-200": "10,49",
   "t200-300m": "11,29",
   "t300-400m": "12,51"
 },
 {
   "Surname": "Steffensen John",
   "Name": "",
   "Nationality": "AUS",
   "Round": "Ht 3",
   "RT": "0,153",
   "t400m": "45,50",
   "t200m": "21,74",
   "Diff.": "2,02",
   "t200-400m": "23,76",
   "t300m": "32,85",
   "t100m": "11,29",
   "t100-200": "10,45",
   "t200-300m": "11,11",
   "t300-400m": "12,65"
 },
 {
   "Surname": "Hurtault",
   "Name": "Erison",
   "Nationality": "DMA",
   "Round": "Ht 2",
   "RT": "0,151",
   "t400m": "45,59",
   "t200m": "",
   "Diff.": "",
   "t200-400m": "",
   "t300m": "32,97",
   "t100m": "",
   "t100-200": "",
   "t200-300m": "",
   "t300-400m": "12,62"
 },
 {
   "Surname": "Yousif",
   "Name": "Rabah",
   "Nationality": "SUD",
   "Round": "Ht 2",
   "RT": "0,175",
   "t400m": "45,63",
   "t200m": "21,80",
   "Diff.": "2,03",
   "t200-400m": "23,83",
   "t300m": "33,07",
   "t100m": "11,33",
   "t100-200": "10,47",
   "t200-300m": "11,27",
   "t300-400m": "12,56"
 }
]